latexthings/__init__.py
latexthings/images.py
latexthings/tables.py
latexthings/wrap.py
latexthings_mkudrin-0.1.0.dist-info/licenses/LICENSE
latexthings_mkudrin-0.1.0.dist-info/METADATA
latexthings_mkudrin-0.1.0.dist-info/WHEEL
latexthings_mkudrin-0.1.0.dist-info/top_level.txt
latexthings_mkudrin-0.1.0.dist-info/RECORD
