Metadata-Version: 2.4
Name: latexthings-mkudrin
Version: 0.1.0
Summary: A Python package for generating LaTeX code for tables, images, and document wrapping
Author: Maxim Kudrin
License: MIT
Project-URL: Homepage, https://github.com/yourusername/latexthings
Classifier: Programming Language :: Python :: 3
Classifier: Operating System :: OS Independent
Requires-Python: >=3.9
License-File: LICENSE
Dynamic: license-file
